pyservicenow/__init__.py
pyservicenow/builder/__init__.py
pyservicenow/builder/_abstract_attachment_request_builder.py
pyservicenow/builder/_abstract_servicenow_entity_request_builder.py
pyservicenow/builder/_attachment_file_request_builder.py
pyservicenow/builder/_attachment_request_builder.py
pyservicenow/builder/_now_request_builder.py
pyservicenow/builder/_table_request_builder.py
pyservicenow/builder/_ui_request_builder.py
pyservicenow/builder/_ui_user_current_user_request_builder.py
pyservicenow/builder/_ui_user_request_builder.py
pyservicenow/builder/knowledge_articles_request_builder.py
pyservicenow/builder/knowledge_request_builder.py
pyservicenow/builder/sn_km_api_request_builder.py
pyservicenow/core/__init__.py
pyservicenow/core/_client_factory.py
pyservicenow/core/_servicenow_client.py
pyservicenow/request/__init__.py
pyservicenow/request/_attachment_entry_collection_request.py
pyservicenow/request/_attachment_entry_request.py
pyservicenow/request/_attachment_file_entry_request.py
pyservicenow/request/_base_attachment_request.py
pyservicenow/request/_base_servicenow_request.py
pyservicenow/request/_base_table_request.py
pyservicenow/request/_knowledge_article_entry_collection_request.py
pyservicenow/request/_knowledge_article_entry_request.py
pyservicenow/request/_servicenow_entry_collection_request.py
pyservicenow/request/_table_entry_collection_request.py
pyservicenow/request/_table_entry_request.py
pyservicenow/request/_ui_user_current_user_request.py
pyservicenow/request/request_extensions/__init__.py
pyservicenow/request/request_extensions/_supports_display_value.py
pyservicenow/request/request_extensions/_supports_exclude_reference_link.py
pyservicenow/request/request_extensions/_supports_no_count.py
pyservicenow/request/request_extensions/_supports_no_domain.py
pyservicenow/request/request_extensions/_supports_suppress_pagination_header.py
pyservicenow/request/request_extensions/_supports_sysparam_category.py
pyservicenow-0.5.0.dist-info/LICENSE
pyservicenow-0.5.0.dist-info/WHEEL
pyservicenow-0.5.0.dist-info/METADATA
pyservicenow-0.5.0.dist-info/RECORD
